{"defaultKeyStatistics":{"annualHoldingsTurnover":{},"enterpriseToRevenue":{"raw":3.562,"fmt":"3.56"},"beta3Year":{},"profitMargins":{"raw":0.15367,"fmt":"15.37%"},"enterpriseToEbitda":{"raw":13.153,"fmt":"13.15"},"52WeekChange":{"raw":-0.013667822,"fmt":"-1.37%"},"morningStarRiskRating":{},"forwardEps":{"raw":8.93,"fmt":"8.93"},"revenueQuarterlyGrowth":{},"sharesOutstanding":{"raw":575196032,"fmt":"575.2M","longFmt":"575,196,032"},"fundInceptionDate":{},"annualReportExpenseRatio":{},"totalAssets":{},"bookValue":{"raw":17.641,"fmt":"17.64"},"sharesShort":{"raw":7222126,"fmt":"7.22M","longFmt":"7,222,126"},"sharesPercentSharesOut":{"raw":0.0126,"fmt":"1.26%"},"fundFamily":null,"lastFiscalYearEnd":{"raw":1577750400,"fmt":"2019-12-31"},"heldPercentInstitutions":{"raw":0.69952005,"fmt":"69.95%"},"netIncomeToCommon":{"raw":4970999808,"fmt":"4.97B","longFmt":"4,970,999,808"},"trailingEps":{"raw":8.523,"fmt":"8.52"},"lastDividendValue":{},"SandP52WeekChange":{"raw":0.11366594,"fmt":"11.37%"},"priceToBook":{"raw":9.290855,"fmt":"9.29"},"heldPercentInsiders":{"raw":0.00182,"fmt":"0.18%"},"nextFiscalYearEnd":{"raw":1640908800,"fmt":"2021-12-31"},"yield":{},"mostRecentQuarter":{"raw":1585612800,"fmt":"2020-03-31"},"shortRatio":{"raw":1.69,"fmt":"1.69"},"sharesShortPreviousMonthDate":{"raw":1588204800,"fmt":"2020-04-30"},"floatShares":{"raw":574517639,"fmt":"574.52M","longFmt":"574,517,639"},"beta":{"raw":0.991726,"fmt":"0.99"},"enterpriseValue":{"raw":115220627456,"fmt":"115.22B","longFmt":"115,220,627,456"},"priceHint":{"raw":2,"fmt":"2","longFmt":"2"},"threeYearAverageReturn":{},"lastSplitDate":{"raw":1064880000,"fmt":"2003-09-30"},"lastSplitFactor":"2:1","legalType":null,"morningStarOverallRating":{},"earningsQuarterlyGrowth":{"raw":0.45,"fmt":"45.00%"},"priceToSalesTrailing12Months":{},"dateShortInterest":{"raw":1590710400,"fmt":"2020-05-29"},"pegRatio":{"raw":14.57,"fmt":"14.57"},"ytdReturn":{},"forwardPE":{"raw":18.353863,"fmt":"18.35"},"maxAge":1,"lastCapGain":{},"shortPercentOfFloat":{"raw":0.0126,"fmt":"1.26%"},"sharesShortPriorMonth":{"raw":6499935,"fmt":"6.5M","longFmt":"6,499,935"},"category":null,"fiveYearAverageReturn":{}},"details":{},"summaryProfile":{"zip":"55144","sector":"Industrials","fullTimeEmployees":96163,"longBusinessSummary":"3M Company develops, manufactures, and markets various products worldwide. It operates through four business segments: Safety & Industrial, Transportation & Electronics, Health Care, and Consumer. The Safety & Industrial segment offers personal safety products, adhesives and tapes, abrasives, closure and masking systems, electrical markets, automotive aftermarket, and roofing granules. The Transportation & Electronics provides electronics, such as display materials and systems, electronic materials solutions; automotive, aerospace, and commercial solutions; advanced materials; and transportation safety products. This segment serves transportation and electronic original equipment manufacturer customers. The Health Care segment offers medical solutions, oral care, separation and purification sciences, health information systems, drug delivery systems, and food safety products. The Consumer segment provides home improvement, home care, and consumer health care products, as well as stationery and office supplies. This segment is also involved in the retail auto care business. The company serves automotive, electronics and automotive electrification, appliance, paper and printing, packaging, food and beverage, construction, medical clinics and hospitals, pharmaceuticals, dental and orthodontic practitioners, health information systems, food manufacturing and testing, consumer and office retail, office business to business, home improvement, drug and pharmacy retail, and other markets. 3M Company was founded in 1902 and is headquartered in St. Paul, Minnesota.","city":"St. Paul","phone":"651-733-1110","state":"MN","country":"United States","companyOfficers":[],"website":"http:\u002F\u002Fwww.3m.com","maxAge":86400,"address1":"3M Center","industry":"Specialty Industrial Machinery"},"recommendationTrend":{"trend":[{"period":"0m","strongBuy":4,"buy":1,"hold":7,"sell":3,"strongSell":0},{"period":"-1m","strongBuy":0,"buy":3,"hold":12,"sell":2,"strongSell":2},{"period":"-2m","strongBuy":0,"buy":2,"hold":14,"sell":2,"strongSell":1},{"period":"-3m","strongBuy":3,"buy":3,"hold":8,"sell":2,"strongSell":2}],"maxAge":86400},"financialsTemplate":{"code":"N","maxAge":1},"earnings":{"maxAge":86400,"earningsChart":{"quarterly":[{"date":"2Q2019","actual":{"raw":2.13,"fmt":"2.13"},"estimate":{"raw":2.05,"fmt":"2.05"}},{"date":"3Q2019","actual":{"raw":2.58,"fmt":"2.58"},"estimate":{"raw":2.49,"fmt":"2.49"}},{"date":"4Q2019","actual":{"raw":2.15,"fmt":"2.15"},"estimate":{"raw":2.1,"fmt":"2.10"}},{"date":"1Q2020","actual":{"raw":2.16,"fmt":"2.16"},"estimate":{"raw":2.03,"fmt":"2.03"}}],"currentQuarterEstimate":{"raw":1.76,"fmt":"1.76"},"currentQuarterEstimateDate":"2Q","currentQuarterEstimateYear":2020,"earningsDate":[{"raw":1595894400,"fmt":"2020-07-28"}]},"financialsChart":{"yearly":[{"date":2016,"revenue":{"raw":30109000000,"fmt":"30.11B","longFmt":"30,109,000,000"},"earnings":{"raw":5050000000,"fmt":"5.05B","longFmt":"5,050,000,000"}},{"date":2017,"revenue":{"raw":31657000000,"fmt":"31.66B","longFmt":"31,657,000,000"},"earnings":{"raw":4858000000,"fmt":"4.86B","longFmt":"4,858,000,000"}},{"date":2018,"revenue":{"raw":32765000000,"fmt":"32.77B","longFmt":"32,765,000,000"},"earnings":{"raw":5349000000,"fmt":"5.35B","longFmt":"5,349,000,000"}},{"date":2019,"revenue":{"raw":32136000000,"fmt":"32.14B","longFmt":"32,136,000,000"},"earnings":{"raw":4570000000,"fmt":"4.57B","longFmt":"4,570,000,000"}}],"quarterly":[{"date":"2Q2019","revenue":{"raw":8171000000,"fmt":"8.17B","longFmt":"8,171,000,000"},"earnings":{"raw":1127000000,"fmt":"1.13B","longFmt":"1,127,000,000"}},{"date":"3Q2019","revenue":{"raw":7991000000,"fmt":"7.99B","longFmt":"7,991,000,000"},"earnings":{"raw":1583000000,"fmt":"1.58B","longFmt":"1,583,000,000"}},{"date":"4Q2019","revenue":{"raw":8111000000,"fmt":"8.11B","longFmt":"8,111,000,000"},"earnings":{"raw":969000000,"fmt":"969M","longFmt":"969,000,000"}},{"date":"1Q2020","revenue":{"raw":8075000000,"fmt":"8.07B","longFmt":"8,075,000,000"},"earnings":{"raw":1292000000,"fmt":"1.29B","longFmt":"1,292,000,000"}}]},"financialCurrency":"USD"},"price":{"quoteSourceName":"Delayed Quote","regularMarketOpen":{"raw":166.9,"fmt":"166.90"},"averageDailyVolume3Month":{"raw":4622528,"fmt":"4.62M","longFmt":"4,622,528"},"exchange":"NYQ","regularMarketTime":1591819201,"volume24Hr":{},"regularMarketDayHigh":{"raw":167.3399,"fmt":"167.34"},"shortName":"3M Company","averageDailyVolume10Day":{"raw":3092657,"fmt":"3.09M","longFmt":"3,092,657"},"longName":"3M Company","regularMarketChange":{"raw":-2.800003,"fmt":"-2.80"},"currencySymbol":"$","regularMarketPreviousClose":{"raw":166.7,"fmt":"166.70"},"postMarketTime":1591832390,"preMarketPrice":{"raw":167.16,"fmt":"167.16"},"preMarketTime":1591795226,"exchangeDataDelayedBy":0,"toCurrency":null,"postMarketChange":{"raw":-1,"fmt":"-1.00"},"postMarketPrice":{"raw":162.9,"fmt":"162.90"},"exchangeName":"NYSE","preMarketChange":{"raw":0.4600067,"fmt":"0.46"},"circulatingSupply":{},"regularMarketDayLow":{"raw":163.81,"fmt":"163.81"},"priceHint":{"raw":2,"fmt":"2","longFmt":"2"},"currency":"USD","regularMarketPrice":{"raw":163.9,"fmt":"163.90"},"regularMarketVolume":{"raw":2378854,"fmt":"2.38M","longFmt":"2,378,854.00"},"lastMarket":null,"regularMarketSource":"DELAYED","openInterest":{},"marketState":"POSTPOST","underlyingSymbol":null,"marketCap":{"raw":94274625536,"fmt":"94.27B","longFmt":"94,274,625,536.00"},"quoteType":"EQUITY","preMarketChangePercent":{"raw":0.0027594885,"fmt":"0.28%"},"volumeAllCurrencies":{},"postMarketSource":"DELAYED","strikePrice":{},"symbol":"MMM","postMarketChangePercent":{"raw":-0.006101282,"fmt":"-0.61%"},"preMarketSource":"DELAYED","maxAge":1,"fromCurrency":null,"regularMarketChangePercent":{"raw":-0.01679666,"fmt":"-1.68%"}},"financialData":{"ebitdaMargins":{"raw":0.2708,"fmt":"27.08%"},"profitMargins":{"raw":0.15367,"fmt":"15.37%"},"grossMargins":{"raw":0.48194999,"fmt":"48.19%"},"operatingCashflow":{"raw":7234999808,"fmt":"7.23B","longFmt":"7,234,999,808"},"revenueGrowth":{"raw":0.027,"fmt":"2.70%"},"operatingMargins":{"raw":0.21955,"fmt":"21.95%"},"ebitda":{"raw":8760000512,"fmt":"8.76B","longFmt":"8,760,000,512"},"targetLowPrice":{"raw":106,"fmt":"106.00"},"recommendationKey":"hold","grossProfits":{"raw":15400000000,"fmt":"15.4B","longFmt":"15,400,000,000"},"freeCashflow":{"raw":4295875072,"fmt":"4.3B","longFmt":"4,295,875,072"},"targetMedianPrice":{"raw":159,"fmt":"159.00"},"currentPrice":{"raw":163.9,"fmt":"163.90"},"earningsGrowth":{"raw":0.47,"fmt":"47.00%"},"currentRatio":{"raw":1.652,"fmt":"1.65"},"returnOnAssets":{"raw":0.10401,"fmt":"10.40%"},"numberOfAnalystOpinions":{"raw":15,"fmt":"15","longFmt":"15"},"targetMeanPrice":{"raw":154.07,"fmt":"154.07"},"debtToEquity":{"raw":228.641,"fmt":"228.64"},"returnOnEquity":{"raw":0.49915,"fmt":"49.92%"},"targetHighPrice":{"raw":180,"fmt":"180.00"},"totalCash":{"raw":4477000192,"fmt":"4.48B","longFmt":"4,477,000,192"},"totalDebt":{"raw":23342000128,"fmt":"23.34B","longFmt":"23,342,000,128"},"totalRevenue":{"raw":32348000256,"fmt":"32.35B","longFmt":"32,348,000,256"},"totalCashPerShare":{"raw":7.783,"fmt":"7.78"},"financialCurrency":"USD","maxAge":86400,"revenuePerShare":{"raw":56.079,"fmt":"56.08"},"quickRatio":{"raw":1.018,"fmt":"1.02"},"recommendationMean":{"raw":3.2,"fmt":"3.20"}},"quoteType":{"exchange":"NYQ","shortName":"3M Company","longName":"3M Company","exchangeTimezoneName":"America\u002FNew_York","exchangeTimezoneShortName":"EDT","isEsgPopulated":false,"gmtOffSetMilliseconds":"-14400000","quoteType":"EQUITY","symbol":"MMM","messageBoardId":"finmb_289194","market":"us_market"},"calendarEvents":{"maxAge":1,"earnings":{"earningsDate":[{"raw":1595894400,"fmt":"2020-07-28"}],"earningsAverage":{"raw":1.76,"fmt":"1.76"},"earningsLow":{"raw":1.52,"fmt":"1.52"},"earningsHigh":{"raw":1.92,"fmt":"1.92"},"revenueAverage":{"raw":7235380000,"fmt":"7.24B","longFmt":"7,235,380,000"},"revenueLow":{"raw":6924000000,"fmt":"6.92B","longFmt":"6,924,000,000"},"revenueHigh":{"raw":7645000000,"fmt":"7.64B","longFmt":"7,645,000,000"}},"exDividendDate":{"raw":1590019200,"fmt":"2020-05-21"},"dividendDate":{"raw":1591920000,"fmt":"2020-06-12"}},"summaryDetail":{"previousClose":{"raw":166.7,"fmt":"166.70"},"regularMarketOpen":{"raw":166.9,"fmt":"166.90"},"twoHundredDayAverage":{"raw":156.8654,"fmt":"156.87"},"trailingAnnualDividendYield":{"raw":0.034733053,"fmt":"3.47%"},"payoutRatio":{"raw":0.6796,"fmt":"67.96%"},"volume24Hr":{},"regularMarketDayHigh":{"raw":167.3399,"fmt":"167.34"},"navPrice":{},"averageDailyVolume10Day":{"raw":3092657,"fmt":"3.09M","longFmt":"3,092,657"},"totalAssets":{},"regularMarketPreviousClose":{"raw":166.7,"fmt":"166.70"},"fiftyDayAverage":{"raw":150.8563,"fmt":"150.86"},"trailingAnnualDividendRate":{"raw":5.79,"fmt":"5.79"},"open":{"raw":166.9,"fmt":"166.90"},"toCurrency":null,"averageVolume10days":{"raw":3092657,"fmt":"3.09M","longFmt":"3,092,657"},"expireDate":{},"yield":{},"algorithm":null,"dividendRate":{"raw":5.88,"fmt":"5.88"},"exDividendDate":{"raw":1590019200,"fmt":"2020-05-21"},"beta":{"raw":0.991726,"fmt":"0.99"},"circulatingSupply":{},"startDate":{},"regularMarketDayLow":{"raw":163.81,"fmt":"163.81"},"priceHint":{"raw":2,"fmt":"2","longFmt":"2"},"currency":"USD","trailingPE":{"raw":19.230318,"fmt":"19.23"},"regularMarketVolume":{"raw":2378854,"fmt":"2.38M","longFmt":"2,378,854"},"lastMarket":null,"maxSupply":{},"openInterest":{},"marketCap":{"raw":94274625536,"fmt":"94.27B","longFmt":"94,274,625,536"},"volumeAllCurrencies":{},"strikePrice":{},"averageVolume":{"raw":4622528,"fmt":"4.62M","longFmt":"4,622,528"},"priceToSalesTrailing12Months":{"raw":2.914388,"fmt":"2.91"},"dayLow":{"raw":163.81,"fmt":"163.81"},"ask":{"raw":163.9,"fmt":"163.90"},"ytdReturn":{},"askSize":{"raw":800,"fmt":"800","longFmt":"800"},"volume":{"raw":2378854,"fmt":"2.38M","longFmt":"2,378,854"},"fiftyTwoWeekHigh":{"raw":187.72,"fmt":"187.72"},"forwardPE":{"raw":18.353863,"fmt":"18.35"},"maxAge":1,"fromCurrency":null,"fiveYearAvgDividendYield":{"raw":2.7,"fmt":"2.70"},"fiftyTwoWeekLow":{"raw":114.04,"fmt":"114.04"},"bid":{"raw":160.07,"fmt":"160.07"},"tradeable":false,"dividendYield":{"raw":0.0353,"fmt":"3.53%"},"bidSize":{"raw":1100,"fmt":"1.1k","longFmt":"1,100"},"dayHigh":{"raw":167.3399,"fmt":"167.34"}}}